vdsinadriver/__init__.py
vdsinadriver-0.0.1.dist-info/LICENSE
vdsinadriver-0.0.1.dist-info/METADATA
vdsinadriver-0.0.1.dist-info/WHEEL
vdsinadriver-0.0.1.dist-info/top_level.txt
vdsinadriver-0.0.1.dist-info/RECORD
