Metadata-Version: 2.1
Name: vdsinadriver
Version: 0.0.1
Summary: Libcloud driver for vdsina.ru
Home-page: https://github.com/thebits/libcloud-vdsina
Author: Sergey Mezentsev
Author-email: thebits@yandex.ru
License: UNLICENSE
Classifier: Intended Audience :: System Administrators
Classifier: Operating System :: OS Independent
Classifier: Programming Language :: Python :: 3
License-File: LICENSE
Requires-Dist: apache-libcloud (>=3.0.0)
